<?xml version="1.0"?>
<save_state>
	<window />
	<input />
	<textures />
	<audio />
	<scene />
	<map />
	<pathfinding />
	<objects />
	<entitymanager>
		<player>
			<player x="45" y="192" life="100" diamonds="0" />
		</player>
		<airEnemy>
			<airEnemy x="612" y="92" life="100" dead="false" />
		</airEnemy>
		<groundEnemy>
			<groundEnemy x="312" y="102" life="100" dead="false" />
		</groundEnemy>
		<checkpoint />
	</entitymanager>
	<collision />
	<gui />
	<fonts />
	<fadetoblack />
	<renderer>
		<camera x="0" y="-82" />
	</renderer>
</save_state>
